KESHAV7x_S_to_T/__init__.py
keshav7x_s_to_t-0.1.dist-info/METADATA
keshav7x_s_to_t-0.1.dist-info/WHEEL
keshav7x_s_to_t-0.1.dist-info/top_level.txt
keshav7x_s_to_t-0.1.dist-info/RECORD
