Metadata-Version: 2.4
Name: KESHAV7x_S_to_T
Version: 0.1
Summary: speech to text package created by keshav
Author: Keshav
Author-email: heyitskeshav@gmail.com
Dynamic: author
Dynamic: author-email
Dynamic: summary
